CHANGES.txt
README.txt
setup.py
docs/LICENSE.GPL
docs/LICENSE.txt
plonerelations/__init__.py
plonerelations.ATField.egg-info/PKG-INFO
plonerelations.ATField.egg-info/SOURCES.txt
plonerelations.ATField.egg-info/dependency_links.txt
plonerelations.ATField.egg-info/namespace_packages.txt
plonerelations.ATField.egg-info/not-zip-safe
plonerelations.ATField.egg-info/requires.txt
plonerelations.ATField.egg-info/top_level.txt
plonerelations/ATField/__init__.py
plonerelations/ATField/configure.zcml
plonerelations/ATField/ploneRelationsATField.py
plonerelations/ATField/ploneRelationsATField.txt
plonerelations/ATField/tests.py