Metadata-Version: 1.0
Name: plonerelations.ATField
Version: 1.0
Summary: ATField for plone.relations
Home-page: http://pypi.python.org/pypi/plonerelations.ATField
Author: Alec Mitchell, Mika Tasich
Author-email: apm13@columbia.edu
License: GPL
Keywords: plone.relation field widget archetypes
Platform: UNKNOWN
Classifier: Framework :: Plone
Classifier: Programming Language :: Python
